<?xml version="1.0" encoding="Windows-1252"?>
<AddFlow Nodes="0" Links="0">
  <Version>2.2.0.0</Version>
  <DefaultLink>
    <Rigid>False</Rigid>
  </DefaultLink>
  <DefaultNode>
    <Shape Type="RectEdgeRaised" Orientation="so_0" />
    <HighlightChildren>False</HighlightChildren>
  </DefaultNode>
  <Node Index="-1" Left="20" Top="3.33333325" Width="66.6666641" Height="26.666666">
    <FillColor>-1</FillColor>
    <Text>door</Text>
    <Tooltip>door</Tooltip>
    <Url>{F99CF121-382A-469A-80C6-3B497B889FB4}</Url>
  </Node>
  <Node Index="-1" Left="120" Top="70" Width="66.6666641" Height="26.666666">
    <FillColor>-1</FillColor>
    <Text>post</Text>
    <Tooltip>post</Tooltip>
    <Url>{6CC14B6C-7232-41F5-A92F-BCCFAC937A45}</Url>
  </Node>
</AddFlow>